README.md
setup.py
slats/__init__.py
slats/config.py
slats/constants.py
slats/exceptions.py
slats/main.py
slats/runtime_args.py
slats/spotify.py
slats/version.py
slats.egg-info/PKG-INFO
slats.egg-info/SOURCES.txt
slats.egg-info/dependency_links.txt
slats.egg-info/entry_points.txt
slats.egg-info/requires.txt
slats.egg-info/top_level.txt