Metadata-Version: 2.1
Name: slats
Version: 1.0.0
Summary: Save local albums to Spotify
Home-page: https://github.com/mwiens91/slats
Author: Matt Wiens
Author-email: mwiens91@gmail.com
License: BSD 3-clause "New" or "Revised License"
Platform: UNKNOWN
Classifier: Development Status :: 4 - Beta
Classifier: Intended Audience :: End Users/Desktop
Classifier: License :: OSI Approved :: BSD License
Classifier: Natural Language :: English
Classifier: Operating System :: Unix
Classifier: Programming Language :: Python
Classifier: Programming Language :: Python :: 3
Classifier: Programming Language :: Python :: 3.6
Classifier: Programming Language :: Python :: 3.7
Classifier: Programming Language :: Python :: 3 :: Only
Requires-Python: >=3.6
